best/__init__.py
best/integration/__init__.py
best/unit/__init__.py
best/unit/conftest.py
best/unit/test_glue_session.py
best/unit/test_glue_session_demo.py
best/unit/test_session_apis.py
tensorflow_manopt-100.0.5.dist-info/LICENSE.txt
tensorflow_manopt-100.0.5.dist-info/METADATA
tensorflow_manopt-100.0.5.dist-info/WHEEL
tensorflow_manopt-100.0.5.dist-info/top_level.txt
tensorflow_manopt-100.0.5.dist-info/RECORD
