Metadata-Version: 2.1
Name: tensorflow-manopt
Version: 100.0.5
Summary: tensorflow_manopt of tensorflow_manopt of tensorflow_manopt
Home-page: UNKNOWN
Author: Aloneee walker
Author-email: aloneewalker@facebook.com
License: UNKNOWN
Platform: UNKNOWN
Classifier: Programming Language :: Python :: 3
Classifier: License :: OSI Approved :: MIT License
Classifier: Operating System :: OS Independent
